{
  "entrypoints": [
    "main"
  ],
  "origins": {
    "320": [
      61,
      401,
      869,
      320
    ],
    "721": [
      721
    ],
    "17896441": [
      320,
      869,
      401
    ],
    "main": [
      354,
      869,
      792
    ],
    "runtime~main": [
      792,
      869,
      354
    ],
    "0058b4c6": [
      849
    ],
    "1df93b7f": [
      869,
      583
    ],
    "1f391b9e": [
      320,
      869,
      61
    ],
    "2735d808": [
      294
    ],
    "393be207": [
      134
    ],
    "3d9c95a4": [
      279
    ],
    "5e95c892": [
      647
    ],
    "68b4307b": [
      137
    ],
    "9907e898": [
      822
    ],
    "a449d16e": [
      431
    ],
    "a7456010": [
      235
    ],
    "a7bd4aaa": [
      98
    ],
    "a94703ab": [
      869,
      48
    ],
    "aba21aa0": [
      742
    ],
    "styles": [
      48,
      61,
      320,
      354,
      401,
      583,
      792,
      869
    ]
  },
  "assets": {
    "48": {
      "js": [
        {
          "file": "assets/js/a94703ab.77f43631.js",
          "hash": "5179bba2a7378f40",
          "publicPath": "/assets/js/a94703ab.77f43631.js"
        }
      ]
    },
    "61": {
      "js": [
        {
          "file": "assets/js/1f391b9e.6105148f.js",
          "hash": "dffb0657f5a9064d",
          "publicPath": "/assets/js/1f391b9e.6105148f.js"
        }
      ]
    },
    "98": {
      "js": [
        {
          "file": "assets/js/a7bd4aaa.3f5a63ce.js",
          "hash": "a42756dc501995c6",
          "publicPath": "/assets/js/a7bd4aaa.3f5a63ce.js"
        }
      ]
    },
    "134": {
      "js": [
        {
          "file": "assets/js/393be207.1b2bb4d5.js",
          "hash": "f589a4b6d6f7fcec",
          "publicPath": "/assets/js/393be207.1b2bb4d5.js"
        }
      ]
    },
    "137": {
      "js": [
        {
          "file": "assets/js/68b4307b.90e23741.js",
          "hash": "1dd05c2c594cceac",
          "publicPath": "/assets/js/68b4307b.90e23741.js"
        }
      ]
    },
    "235": {
      "js": [
        {
          "file": "assets/js/a7456010.14e53a54.js",
          "hash": "eb31d7160eaa3d52",
          "publicPath": "/assets/js/a7456010.14e53a54.js"
        }
      ]
    },
    "279": {
      "js": [
        {
          "file": "assets/js/3d9c95a4.baabe12a.js",
          "hash": "3a9fb0d58c8c5436",
          "publicPath": "/assets/js/3d9c95a4.baabe12a.js"
        }
      ]
    },
    "294": {
      "js": [
        {
          "file": "assets/js/2735d808.9a8594ce.js",
          "hash": "0c9d01e73b071f1e",
          "publicPath": "/assets/js/2735d808.9a8594ce.js"
        }
      ]
    },
    "320": {
      "js": [
        {
          "file": "assets/js/320.827bd2d2.js",
          "hash": "8a9be608c7f3901b",
          "publicPath": "/assets/js/320.827bd2d2.js"
        }
      ]
    },
    "354": {
      "js": [
        {
          "file": "assets/js/runtime~main.d3c3ef80.js",
          "hash": "2fe7dd62c7071f7b",
          "publicPath": "/assets/js/runtime~main.d3c3ef80.js"
        }
      ]
    },
    "401": {
      "js": [
        {
          "file": "assets/js/17896441.ab73820c.js",
          "hash": "80a2d4f256ff69d3",
          "publicPath": "/assets/js/17896441.ab73820c.js"
        }
      ]
    },
    "431": {
      "js": [
        {
          "file": "assets/js/a449d16e.8de7cbda.js",
          "hash": "ac3d7f31e545e0f1",
          "publicPath": "/assets/js/a449d16e.8de7cbda.js"
        }
      ]
    },
    "583": {
      "js": [
        {
          "file": "assets/js/1df93b7f.59c9aa30.js",
          "hash": "e747240fac40b3ac",
          "publicPath": "/assets/js/1df93b7f.59c9aa30.js"
        }
      ]
    },
    "647": {
      "js": [
        {
          "file": "assets/js/5e95c892.24995716.js",
          "hash": "0c0a8c0fb705c6a6",
          "publicPath": "/assets/js/5e95c892.24995716.js"
        }
      ]
    },
    "721": {
      "js": [
        {
          "file": "assets/js/721.b298b5da.js",
          "hash": "af8d5f4c19362436",
          "publicPath": "/assets/js/721.b298b5da.js"
        }
      ]
    },
    "742": {
      "js": [
        {
          "file": "assets/js/aba21aa0.a260077a.js",
          "hash": "febd154ccf9ee7d0",
          "publicPath": "/assets/js/aba21aa0.a260077a.js"
        }
      ]
    },
    "792": {
      "js": [
        {
          "file": "assets/js/main.60c38905.js",
          "hash": "b9cb47774706f61c",
          "publicPath": "/assets/js/main.60c38905.js"
        }
      ]
    },
    "822": {
      "js": [
        {
          "file": "assets/js/9907e898.97e81a5c.js",
          "hash": "f59ac2b8228c71cc",
          "publicPath": "/assets/js/9907e898.97e81a5c.js"
        }
      ]
    },
    "849": {
      "js": [
        {
          "file": "assets/js/0058b4c6.d2024799.js",
          "hash": "f825434d9de03cd0",
          "publicPath": "/assets/js/0058b4c6.d2024799.js"
        }
      ]
    },
    "869": {
      "css": [
        {
          "file": "assets/css/styles.0ace63c3.css",
          "hash": "95c5ffd124d72152",
          "publicPath": "/assets/css/styles.0ace63c3.css"
        }
      ]
    }
  }
}